downloader_plus/__init__.py
Downloader_plus-0.0.4.dist-info/METADATA
Downloader_plus-0.0.4.dist-info/WHEEL
Downloader_plus-0.0.4.dist-info/top_level.txt
Downloader_plus-0.0.4.dist-info/RECORD
