Metadata-Version: 2.1
Name: Downloader-plus
Version: 0.0.4
Home-page: https://github.com/Win11BSOD/downloader_plus
Author: Guo Minghao
Author-email: qu11182021@outlook.com
